flake8_if_expr/__init__.py
flake8_if_expr-1.0.4.dist-info/entry_points.txt
flake8_if_expr-1.0.4.dist-info/LICENSE
flake8_if_expr-1.0.4.dist-info/WHEEL
flake8_if_expr-1.0.4.dist-info/METADATA
flake8_if_expr-1.0.4.dist-info/RECORD
