Metadata-Version: 2.1
Name: flake8-if-expr
Version: 1.0.4
Summary: The plugin checks `if expressions` (ternary operator)
Home-page: https://pypi.org/project/flake8-if-expr
License: MIT
Keywords: flake8,linter
Author: Afonasev Evgeniy
Author-email: ea.afonasev@gmail.com
Requires-Python: >=3.6,<4.0
Classifier: License :: OSI Approved :: MIT License
Classifier: Programming Language :: Python :: 3
Classifier: Programming Language :: Python :: 3.6
Classifier: Programming Language :: Python :: 3.7
Classifier: Programming Language :: Python :: 3.8
Requires-Dist: flake8-plugin-utils (>=1.0,<2.0)
Project-URL: Repository, https://github.com/afonasev/flake8-if-expr
